oa_zero_sum.py
oa_zero_sum-0.0.1.dist-info/LICENSE
oa_zero_sum-0.0.1.dist-info/METADATA
oa_zero_sum-0.0.1.dist-info/WHEEL
oa_zero_sum-0.0.1.dist-info/top_level.txt
oa_zero_sum-0.0.1.dist-info/RECORD
